{
  "type": "Program",
  "body": [
    {
      "type": "ImportDeclaration",
      "specifiers": [
        {
          "type": "ImportSpecifier",
          "local": {
            "type": "Identifier",
            "name": "routePrefixer",
            "range": [
              8,
              21
            ],
            "loc": {
              "start": {
                "line": 1,
                "column": 8
              },
              "end": {
                "line": 1,
                "column": 21
              }
            }
          },
          "imported": {
            "type": "Identifier",
            "name": "routePrefixer",
            "range": [
              8,
              21
            ],
            "loc": {
              "start": {
                "line": 1,
                "column": 8
              },
              "end": {
                "line": 1,
                "column": 21
              }
            }
          },
          "range": [
            8,
            21
          ],
          "loc": {
            "start": {
              "line": 1,
              "column": 8
            },
            "end": {
              "line": 1,
              "column": 21
            }
          }
        }
      ],
      "source": {
        "type": "Literal",
        "value": "../../helpers",
        "raw": "'../../helpers'",
        "range": [
          28,
          43
        ],
        "loc": {
          "start": {
            "line": 1,
            "column": 28
          },
          "end": {
            "line": 1,
            "column": 43
          }
        }
      },
      "range": [
        0,
        44
      ],
      "loc": {
        "start": {
          "line": 1,
          "column": 0
        },
        "end": {
          "line": 1,
          "column": 44
        }
      }
    },
    {
      "type": "ImportDeclaration",
      "specifiers": [
        {
          "type": "ImportDefaultSpecifier",
          "local": {
            "type": "Identifier",
            "name": "Models",
            "range": [
              52,
              58
            ],
            "loc": {
              "start": {
                "line": 2,
                "column": 7
              },
              "end": {
                "line": 2,
                "column": 13
              }
            }
          },
          "range": [
            52,
            58
          ],
          "loc": {
            "start": {
              "line": 2,
              "column": 7
            },
            "end": {
              "line": 2,
              "column": 13
            }
          }
        }
      ],
      "source": {
        "type": "Literal",
        "value": "../../models",
        "raw": "'../../models'",
        "range": [
          64,
          78
        ],
        "loc": {
          "start": {
            "line": 2,
            "column": 19
          },
          "end": {
            "line": 2,
            "column": 33
          }
        }
      },
      "range": [
        45,
        79
      ],
      "loc": {
        "start": {
          "line": 2,
          "column": 0
        },
        "end": {
          "line": 2,
          "column": 34
        }
      }
    },
    {
      "type": "ImportDeclaration",
      "specifiers": [
        {
          "type": "ImportDefaultSpecifier",
          "local": {
            "type": "Identifier",
            "name": "localAuth",
            "range": [
              88,
              97
            ],
            "loc": {
              "start": {
                "line": 4,
                "column": 7
              },
              "end": {
                "line": 4,
                "column": 16
              }
            }
          },
          "range": [
            88,
            97
          ],
          "loc": {
            "start": {
              "line": 4,
              "column": 7
            },
            "end": {
              "line": 4,
              "column": 16
            }
          }
        }
      ],
      "source": {
        "type": "Literal",
        "value": "./localAuth",
        "raw": "'./localAuth'",
        "range": [
          103,
          116
        ],
        "loc": {
          "start": {
            "line": 4,
            "column": 22
          },
          "end": {
            "line": 4,
            "column": 35
          }
        }
      },
      "range": [
        81,
        117
      ],
      "loc": {
        "start": {
          "line": 4,
          "column": 0
        },
        "end": {
          "line": 4,
          "column": 36
        }
      }
    },
    {
      "type": "ImportDeclaration",
      "specifiers": [
        {
          "type": "ImportDefaultSpecifier",
          "local": {
            "type": "Identifier",
            "name": "hello",
            "range": [
              125,
              130
            ],
            "loc": {
              "start": {
                "line": 5,
                "column": 7
              },
              "end": {
                "line": 5,
                "column": 12
              }
            }
          },
          "range": [
            125,
            130
          ],
          "loc": {
            "start": {
              "line": 5,
              "column": 7
            },
            "end": {
              "line": 5,
              "column": 12
            }
          }
        }
      ],
      "source": {
        "type": "Literal",
        "value": "./hello",
        "raw": "'./hello'",
        "range": [
          136,
          145
        ],
        "loc": {
          "start": {
            "line": 5,
            "column": 18
          },
          "end": {
            "line": 5,
            "column": 27
          }
        }
      },
      "range": [
        118,
        146
      ],
      "loc": {
        "start": {
          "line": 5,
          "column": 0
        },
        "end": {
          "line": 5,
          "column": 28
        }
      }
    },
    {
      "type": "ImportDeclaration",
      "specifiers": [
        {
          "type": "ImportDefaultSpecifier",
          "local": {
            "type": "Identifier",
            "name": "posts",
            "range": [
              154,
              159
            ],
            "loc": {
              "start": {
                "line": 6,
                "column": 7
              },
              "end": {
                "line": 6,
                "column": 12
              }
            }
          },
          "range": [
            154,
            159
          ],
          "loc": {
            "start": {
              "line": 6,
              "column": 7
            },
            "end": {
              "line": 6,
              "column": 12
            }
          }
        }
      ],
      "source": {
        "type": "Literal",
        "value": "./posts",
        "raw": "'./posts'",
        "range": [
          165,
          174
        ],
        "loc": {
          "start": {
            "line": 6,
            "column": 18
          },
          "end": {
            "line": 6,
            "column": 27
          }
        }
      },
      "range": [
        147,
        175
      ],
      "loc": {
        "start": {
          "line": 6,
          "column": 0
        },
        "end": {
          "line": 6,
          "column": 28
        }
      },
      "trailingComments": [
        {
          "type": "Block",
          "value": "*\n * Mount all api v1 routes\n ",
          "range": [
            177,
            211
          ],
          "loc": {
            "start": {
              "line": 8,
              "column": 0
            },
            "end": {
              "line": 10,
              "column": 3
            }
          }
        }
      ]
    },
    {
      "type": "Identifier",
      "declarations": [
        {
          "type": "VariableDeclarator",
          "id": {
            "type": "Identifier",
            "name": "apiV1",
            "range": [
              218,
              223
            ],
            "loc": {
              "start": {
                "line": 11,
                "column": 6
              },
              "end": {
                "line": 11,
                "column": 11
              }
            }
          },
          "init": {
            "type": "ArrowFunctionExpression",
            "id": null,
            "params": [
              {
                "type": "Identifier",
                "name": "server",
                "range": [
                  227,
                  233
                ],
                "loc": {
                  "start": {
                    "line": 11,
                    "column": 15
                  },
                  "end": {
                    "line": 11,
                    "column": 21
                  }
                }
              }
            ],
            "body": {
              "type": "BlockStatement",
              "body": [
                {
                  "type": "ReturnStatement",
                  "argument": {
                    "type": "CallExpression",
                    "callee": {
                      "type": "Identifier",
                      "name": "routePrefixer",
                      "range": [
                        249,
                        262
                      ],
                      "loc": {
                        "start": {
                          "line": 12,
                          "column": 9
                        },
                        "end": {
                          "line": 12,
                          "column": 22
                        }
                      }
                    },
                    "arguments": [
                      {
                        "type": "Literal",
                        "value": "/v1",
                        "raw": "'/v1'",
                        "range": [
                          263,
                          268
                        ],
                        "loc": {
                          "start": {
                            "line": 12,
                            "column": 23
                          },
                          "end": {
                            "line": 12,
                            "column": 28
                          }
                        }
                      },
                      {
                        "type": "ArrayExpression",
                        "elements": [
                          {
                            "type": "SpreadElement",
                            "argument": {
                              "type": "Identifier",
                              "name": "localAuth",
                              "range": [
                                279,
                                288
                              ],
                              "loc": {
                                "start": {
                                  "line": 13,
                                  "column": 7
                                },
                                "end": {
                                  "line": 13,
                                  "column": 16
                                }
                              }
                            },
                            "range": [
                              276,
                              288
                            ],
                            "loc": {
                              "start": {
                                "line": 13,
                                "column": 4
                              },
                              "end": {
                                "line": 13,
                                "column": 16
                              }
                            }
                          },
                          {
                            "type": "SpreadElement",
                            "argument": {
                              "type": "CallExpression",
                              "callee": {
                                "type": "Identifier",
                                "name": "hello",
                                "range": [
                                  297,
                                  302
                                ],
                                "loc": {
                                  "start": {
                                    "line": 14,
                                    "column": 7
                                  },
                                  "end": {
                                    "line": 14,
                                    "column": 12
                                  }
                                }
                              },
                              "arguments": [
                                {
                                  "type": "Identifier",
                                  "name": "server",
                                  "range": [
                                    303,
                                    309
                                  ],
                                  "loc": {
                                    "start": {
                                      "line": 14,
                                      "column": 13
                                    },
                                    "end": {
                                      "line": 14,
                                      "column": 19
                                    }
                                  }
                                },
                                {
                                  "type": "Identifier",
                                  "name": "Models",
                                  "range": [
                                    311,
                                    317
                                  ],
                                  "loc": {
                                    "start": {
                                      "line": 14,
                                      "column": 21
                                    },
                                    "end": {
                                      "line": 14,
                                      "column": 27
                                    }
                                  }
                                }
                              ],
                              "range": [
                                297,
                                318
                              ],
                              "loc": {
                                "start": {
                                  "line": 14,
                                  "column": 7
                                },
                                "end": {
                                  "line": 14,
                                  "column": 28
                                }
                              }
                            },
                            "range": [
                              294,
                              318
                            ],
                            "loc": {
                              "start": {
                                "line": 14,
                                "column": 4
                              },
                              "end": {
                                "line": 14,
                                "column": 28
                              }
                            }
                          },
                          {
                            "type": "SpreadElement",
                            "argument": {
                              "type": "CallExpression",
                              "callee": {
                                "type": "Identifier",
                                "name": "posts",
                                "range": [
                                  327,
                                  332
                                ],
                                "loc": {
                                  "start": {
                                    "line": 15,
                                    "column": 7
                                  },
                                  "end": {
                                    "line": 15,
                                    "column": 12
                                  }
                                }
                              },
                              "arguments": [
                                {
                                  "type": "Identifier",
                                  "name": "server",
                                  "range": [
                                    333,
                                    339
                                  ],
                                  "loc": {
                                    "start": {
                                      "line": 15,
                                      "column": 13
                                    },
                                    "end": {
                                      "line": 15,
                                      "column": 19
                                    }
                                  }
                                },
                                {
                                  "type": "Identifier",
                                  "name": "Models",
                                  "range": [
                                    341,
                                    347
                                  ],
                                  "loc": {
                                    "start": {
                                      "line": 15,
                                      "column": 21
                                    },
                                    "end": {
                                      "line": 15,
                                      "column": 27
                                    }
                                  }
                                }
                              ],
                              "range": [
                                327,
                                348
                              ],
                              "loc": {
                                "start": {
                                  "line": 15,
                                  "column": 7
                                },
                                "end": {
                                  "line": 15,
                                  "column": 28
                                }
                              }
                            },
                            "range": [
                              324,
                              348
                            ],
                            "loc": {
                              "start": {
                                "line": 15,
                                "column": 4
                              },
                              "end": {
                                "line": 15,
                                "column": 28
                              }
                            }
                          }
                        ],
                        "range": [
                          270,
                          353
                        ],
                        "loc": {
                          "start": {
                            "line": 12,
                            "column": 30
                          },
                          "end": {
                            "line": 16,
                            "column": 3
                          }
                        }
                      }
                    ],
                    "range": [
                      249,
                      354
                    ],
                    "loc": {
                      "start": {
                        "line": 12,
                        "column": 9
                      },
                      "end": {
                        "line": 16,
                        "column": 4
                      }
                    }
                  },
                  "range": [
                    242,
                    355
                  ],
                  "loc": {
                    "start": {
                      "line": 12,
                      "column": 2
                    },
                    "end": {
                      "line": 16,
                      "column": 5
                    }
                  }
                }
              ],
              "range": [
                238,
                357
              ],
              "loc": {
                "start": {
                  "line": 11,
                  "column": 26
                },
                "end": {
                  "line": 17,
                  "column": 1
                }
              }
            },
            "generator": false,
            "expression": false,
            "range": [
              226,
              357
            ],
            "loc": {
              "start": {
                "line": 11,
                "column": 14
              },
              "end": {
                "line": 17,
                "column": 1
              }
            }
          },
          "range": [
            218,
            357
          ],
          "loc": {
            "start": {
              "line": 11,
              "column": 6
            },
            "end": {
              "line": 17,
              "column": 1
            }
          }
        }
      ],
      "kind": "const",
      "range": [
        212,
        358
      ],
      "loc": {
        "start": {
          "line": 11,
          "column": 0
        },
        "end": {
          "line": 17,
          "column": 2
        }
      },
      "leadingComments": [],
      "name": "_",
      "trailingComments": []
    },
    {
      "type": "Identifier",
      "declaration": {
        "type": "Identifier",
        "name": "apiV1",
        "range": [
          375,
          380
        ],
        "loc": {
          "start": {
            "line": 19,
            "column": 15
          },
          "end": {
            "line": 19,
            "column": 20
          }
        }
      },
      "range": [
        360,
        381
      ],
      "loc": {
        "start": {
          "line": 19,
          "column": 0
        },
        "end": {
          "line": 19,
          "column": 21
        }
      },
      "name": "_",
      "leadingComments": [],
      "trailingComments": []
    },
    {
      "type": "ExportDefaultDeclaration",
      "declaration": {
        "type": "VariableDeclaration",
        "declarations": [
          {
            "type": "VariableDeclarator",
            "id": {
              "type": "Identifier",
              "name": "apiV1",
              "range": [
                218,
                223
              ],
              "loc": {
                "start": {
                  "line": 11,
                  "column": 6
                },
                "end": {
                  "line": 11,
                  "column": 11
                }
              }
            },
            "init": {
              "type": "ArrowFunctionExpression",
              "id": null,
              "params": [
                {
                  "type": "Identifier",
                  "name": "server",
                  "range": [
                    227,
                    233
                  ],
                  "loc": {
                    "start": {
                      "line": 11,
                      "column": 15
                    },
                    "end": {
                      "line": 11,
                      "column": 21
                    }
                  }
                }
              ],
              "body": {
                "type": "BlockStatement",
                "body": [
                  {
                    "type": "ReturnStatement",
                    "argument": {
                      "type": "CallExpression",
                      "callee": {
                        "type": "Identifier",
                        "name": "routePrefixer",
                        "range": [
                          249,
                          262
                        ],
                        "loc": {
                          "start": {
                            "line": 12,
                            "column": 9
                          },
                          "end": {
                            "line": 12,
                            "column": 22
                          }
                        }
                      },
                      "arguments": [
                        {
                          "type": "Literal",
                          "value": "/v1",
                          "raw": "'/v1'",
                          "range": [
                            263,
                            268
                          ],
                          "loc": {
                            "start": {
                              "line": 12,
                              "column": 23
                            },
                            "end": {
                              "line": 12,
                              "column": 28
                            }
                          }
                        },
                        {
                          "type": "ArrayExpression",
                          "elements": [
                            {
                              "type": "SpreadElement",
                              "argument": {
                                "type": "Identifier",
                                "name": "localAuth",
                                "range": [
                                  279,
                                  288
                                ],
                                "loc": {
                                  "start": {
                                    "line": 13,
                                    "column": 7
                                  },
                                  "end": {
                                    "line": 13,
                                    "column": 16
                                  }
                                }
                              },
                              "range": [
                                276,
                                288
                              ],
                              "loc": {
                                "start": {
                                  "line": 13,
                                  "column": 4
                                },
                                "end": {
                                  "line": 13,
                                  "column": 16
                                }
                              }
                            },
                            {
                              "type": "SpreadElement",
                              "argument": {
                                "type": "CallExpression",
                                "callee": {
                                  "type": "Identifier",
                                  "name": "hello",
                                  "range": [
                                    297,
                                    302
                                  ],
                                  "loc": {
                                    "start": {
                                      "line": 14,
                                      "column": 7
                                    },
                                    "end": {
                                      "line": 14,
                                      "column": 12
                                    }
                                  }
                                },
                                "arguments": [
                                  {
                                    "type": "Identifier",
                                    "name": "server",
                                    "range": [
                                      303,
                                      309
                                    ],
                                    "loc": {
                                      "start": {
                                        "line": 14,
                                        "column": 13
                                      },
                                      "end": {
                                        "line": 14,
                                        "column": 19
                                      }
                                    }
                                  },
                                  {
                                    "type": "Identifier",
                                    "name": "Models",
                                    "range": [
                                      311,
                                      317
                                    ],
                                    "loc": {
                                      "start": {
                                        "line": 14,
                                        "column": 21
                                      },
                                      "end": {
                                        "line": 14,
                                        "column": 27
                                      }
                                    }
                                  }
                                ],
                                "range": [
                                  297,
                                  318
                                ],
                                "loc": {
                                  "start": {
                                    "line": 14,
                                    "column": 7
                                  },
                                  "end": {
                                    "line": 14,
                                    "column": 28
                                  }
                                }
                              },
                              "range": [
                                294,
                                318
                              ],
                              "loc": {
                                "start": {
                                  "line": 14,
                                  "column": 4
                                },
                                "end": {
                                  "line": 14,
                                  "column": 28
                                }
                              }
                            },
                            {
                              "type": "SpreadElement",
                              "argument": {
                                "type": "CallExpression",
                                "callee": {
                                  "type": "Identifier",
                                  "name": "posts",
                                  "range": [
                                    327,
                                    332
                                  ],
                                  "loc": {
                                    "start": {
                                      "line": 15,
                                      "column": 7
                                    },
                                    "end": {
                                      "line": 15,
                                      "column": 12
                                    }
                                  }
                                },
                                "arguments": [
                                  {
                                    "type": "Identifier",
                                    "name": "server",
                                    "range": [
                                      333,
                                      339
                                    ],
                                    "loc": {
                                      "start": {
                                        "line": 15,
                                        "column": 13
                                      },
                                      "end": {
                                        "line": 15,
                                        "column": 19
                                      }
                                    }
                                  },
                                  {
                                    "type": "Identifier",
                                    "name": "Models",
                                    "range": [
                                      341,
                                      347
                                    ],
                                    "loc": {
                                      "start": {
                                        "line": 15,
                                        "column": 21
                                      },
                                      "end": {
                                        "line": 15,
                                        "column": 27
                                      }
                                    }
                                  }
                                ],
                                "range": [
                                  327,
                                  348
                                ],
                                "loc": {
                                  "start": {
                                    "line": 15,
                                    "column": 7
                                  },
                                  "end": {
                                    "line": 15,
                                    "column": 28
                                  }
                                }
                              },
                              "range": [
                                324,
                                348
                              ],
                              "loc": {
                                "start": {
                                  "line": 15,
                                  "column": 4
                                },
                                "end": {
                                  "line": 15,
                                  "column": 28
                                }
                              }
                            }
                          ],
                          "range": [
                            270,
                            353
                          ],
                          "loc": {
                            "start": {
                              "line": 12,
                              "column": 30
                            },
                            "end": {
                              "line": 16,
                              "column": 3
                            }
                          }
                        }
                      ],
                      "range": [
                        249,
                        354
                      ],
                      "loc": {
                        "start": {
                          "line": 12,
                          "column": 9
                        },
                        "end": {
                          "line": 16,
                          "column": 4
                        }
                      }
                    },
                    "range": [
                      242,
                      355
                    ],
                    "loc": {
                      "start": {
                        "line": 12,
                        "column": 2
                      },
                      "end": {
                        "line": 16,
                        "column": 5
                      }
                    }
                  }
                ],
                "range": [
                  238,
                  357
                ],
                "loc": {
                  "start": {
                    "line": 11,
                    "column": 26
                  },
                  "end": {
                    "line": 17,
                    "column": 1
                  }
                }
              },
              "generator": false,
              "expression": false,
              "range": [
                226,
                357
              ],
              "loc": {
                "start": {
                  "line": 11,
                  "column": 14
                },
                "end": {
                  "line": 17,
                  "column": 1
                }
              }
            },
            "range": [
              218,
              357
            ],
            "loc": {
              "start": {
                "line": 11,
                "column": 6
              },
              "end": {
                "line": 17,
                "column": 1
              }
            }
          }
        ],
        "kind": "const",
        "range": [
          212,
          358
        ],
        "loc": {
          "start": {
            "line": 11,
            "column": 0
          },
          "end": {
            "line": 17,
            "column": 2
          }
        },
        "leadingComments": [
          {
            "type": "Block",
            "value": "*\n * Mount all api v1 routes\n ",
            "range": [
              177,
              211
            ],
            "loc": {
              "start": {
                "line": 8,
                "column": 0
              },
              "end": {
                "line": 10,
                "column": 3
              }
            }
          }
        ],
        "trailingComments": []
      },
      "range": [
        360,
        381
      ],
      "loc": {
        "start": {
          "line": 19,
          "column": 0
        },
        "end": {
          "line": 19,
          "column": 21
        }
      }
    }
  ],
  "sourceType": "module",
  "range": [
    0,
    381
  ],
  "loc": {
    "start": {
      "line": 1,
      "column": 0
    },
    "end": {
      "line": 19,
      "column": 21
    }
  },
  "comments": [
    {
      "type": "Block",
      "value": "*\n * Mount all api v1 routes\n ",
      "range": [
        177,
        211
      ],
      "loc": {
        "start": {
          "line": 8,
          "column": 0
        },
        "end": {
          "line": 10,
          "column": 3
        }
      }
    }
  ]
}